setup.py
collective/__init__.py
collective.recipe.mxodbc.egg-info/PKG-INFO
collective.recipe.mxodbc.egg-info/SOURCES.txt
collective.recipe.mxodbc.egg-info/dependency_links.txt
collective.recipe.mxodbc.egg-info/entry_points.txt
collective.recipe.mxodbc.egg-info/namespace_packages.txt
collective.recipe.mxodbc.egg-info/requires.txt
collective.recipe.mxodbc.egg-info/top_level.txt
collective.recipe.mxodbc.egg-info/zip-safe
collective/recipe/__init__.py
collective/recipe/mxodbc/__init__.py