Metadata-Version: 1.0
Name: collective.recipe.mxodbc
Version: 0.4
Summary: A buildout recipe to install eGenix mx.ODBC and a licence
Home-page: http://svn.plone.org/svn/collective/buildout/collective.recipe.mxodbc
Author: Jarn
Author-email: info@jarn.com
License: GPL
Keywords: build mx.ODBC
Platform: UNKNOWN
Classifier: Development Status :: 3 - Alpha
Classifier: Environment :: Plugins
Classifier: Intended Audience :: System Administrators
Classifier: Framework :: Buildout
Classifier: License :: OSI Approved :: GNU General Public License (GPL)
Classifier: Programming Language :: Python
Classifier: Topic :: Database
Classifier: Topic :: System :: Installation/Setup
Classifier: Topic :: Software Development :: Libraries :: Python Modules
